MANIFEST.in
README.txt
setup.cfg
setup.py
collective/__init__.py
collective.sphinx.autoatschema.egg-info/PKG-INFO
collective.sphinx.autoatschema.egg-info/SOURCES.txt
collective.sphinx.autoatschema.egg-info/dependency_links.txt
collective.sphinx.autoatschema.egg-info/namespace_packages.txt
collective.sphinx.autoatschema.egg-info/not-zip-safe
collective.sphinx.autoatschema.egg-info/requires.txt
collective.sphinx.autoatschema.egg-info/top_level.txt
collective/sphinx/__init__.py
collective/sphinx/autoatschema/__init__.py