Metadata-Version: 1.0
Name: collective.sphinx.autoatschema
Version: 0.1
Summary: Sphinx extension for archetypes schema
Home-page: http://
Author: Rok Garbas
Author-email: rok@garbas.si
License: GPL
Keywords: zope archetypes sphinx documentation
Platform: UNKNOWN
Classifier: Intended Audience :: Developers
Classifier: Programming Language :: Python
Classifier: License :: OSI Approved :: GNU General Public License (GPL)
